[{"id":1,"type":"t"},{"id":2,"type":"t"},{"id":3,"type":"t"},{"id":4,"type":"c"},{"id":5,"type":"c"},{"id":6,"type":"c"},{"id":7,"type":"t"},{"id":8,"type":"c"},{"id":9,"type":"t"},{"id":10,"type":"t"},{"id":11,"type":"t"},{"id":12,"type":"t"},{"id":13,"type":"t"},{"id":14,"type":"t"},{"id":15,"type":"t"},{"id":16,"type":"t"},{"id":17,"type":"t"},{"id":18,"type":"t"},{"id":19,"type":"t"},{"id":20,"type":"t"},{"id":21,"type":"t"},{"id":22,"type":"t"},{"id":23,"type":"t"},{"id":24,"type":"t"},{"id":25,"type":"t"},{"id":26,"type":"t"},{"id":27,"type":"t"},{"id":28,"type":"t"},{"id":29,"type":"t"},{"id":30,"type":"t"},{"id":31,"type":"t"}]
